Workbook
Name aport: SIM!$C$17
Name patrimonio: SIM!$B$20
Name qtde_anos: SIM!$C$18
Name rendimento_carteira: SIM!$C$25
Name salario: SIM!$C$24
Name sugestao_investimento: SIM!$C$26
Name tx_mensal: SIM!$C$19

Sheet SIM
B16: Investimento Mensal
B17: Quanto investir? | C17: 750
A18: 2 | B18: Por quanto tempo? | C18: 5
A19: 5 | B19: TR Mensal? | C19: 0.01079
A20: 10 | B20: Patrimônio Acumulado? | C20: =FV(tx_mensal,qtde_anos*12,aport*-1) -> 62832.685
A21: 20 | B21: Dividendos Mensais? | C21: =C20*C25 -> 628.32685
A22: 30
B23: Configurações
B24: Salário | C24: 5000
B25: Rendimento da Carteira | C25: 0.01
B26: Sugestão de Investimento | C26: =C24*0.3 -> 1500
B28: Cenários | D28: Dividendos
B29: 2 anos | C29: =FV($C$19,$A18*12,$C$17*-1) -> 20420.72 | D29: =C29*rendimento_carteira -> 204.2072
B30: 5 anos | C30: =FV($C$19,$A19*12,$C$17*-1) -> 62832.685 | D30: =C30*rendimento_carteira -> 628.32685
B31: 10 anos | C31: =FV($C$19,$A20*12,$C$17*-1) -> 182463.16 | D31: =C31*rendimento_carteira -> 1824.6316
B32: 20 anos | C32: =FV($C$19,$A21*12,$C$17*-1) -> 843898.8 | D32: =C32*rendimento_carteira -> 8438.988
B33: 30 anos | C33: =FV($C$19,$A22*12,$C$17*-1) -> 3241627.2 | D33: =C33*rendimento_carteira -> 32416.272
B37: Perfis de Investimento | C37: Agressivo
B38: Valor a ser Investido po mês | C38: =aport -> 750
B40: Tipo de FI | C40: Percentual Sugerido | D40: Valores
B41: Papel | C41: =VLOOKUP($C$37&"-"&B41,BaseApoio!$A$1:$D$19,4,0) -> 0.5 | D41: =C41*$C$38 -> 375
B42: Tijolo | C42: =VLOOKUP($C$37&"-"&B42,BaseApoio!$A$1:$D$19,4,0) -> 0.1 | D42: =C42*$C$38 -> 75
B43: Híbridos | C43: =VLOOKUP($C$37&"-"&B43,BaseApoio!$A$1:$D$19,4,0) -> 0.05 | D43: =C43*$C$38 -> 37.5
B44: Desevolvimento | C44: =VLOOKUP($C$37&"-"&B44,BaseApoio!$A$1:$D$19,4,0) -> 0.2 | D44: =C44*$C$38 -> 150
B45: FOFs | C45: =VLOOKUP($C$37&"-"&B45,BaseApoio!$A$1:$D$19,4,0) -> 0.05 | D45: =C45*$C$38 -> 37.5
B46: Hotelaria | C46: =VLOOKUP($C$37&"-"&B46,BaseApoio!$A$1:$D$19,4,0) -> 0.1 | D46: =C46*$C$38 -> 75
D47: =SUM(D41:D46) -> 750

Sheet BaseApoio
A1: chave | B1: Perfil | C1: Tipo de FI | D1: %
A2: =B2&"-"&C2 -> Conservador-Papel | B2: Conservador | C2: Papel | D2: 0.3
A3: =B3&"-"&C3 -> Conservador-Tijolo | B3: Conservador | C3: Tijolo | D3: 0.5
A4: =B4&"-"&C4 -> Conservador-Híbridos | B4: Conservador | C4: Híbridos | D4: 0.1
A5: =B5&"-"&C5 -> Conservador-Desevolvimento | B5: Conservador | C5: Desevolvimento | D5: 0
A6: =B6&"-"&C6 -> Conservador-FOFs | B6: Conservador | C6: FOFs | D6: 0.1
A7: =B7&"-"&C7 -> Conservador-Hotelaria | B7: Conservador | C7: Hotelaria | D7: 0
A8: =B8&"-"&C8 -> Moderado-Papel | B8: Moderado | C8: Papel | D8: 0.32
A9: =B9&"-"&C9 -> Moderado-Tijolo | B9: Moderado | C9: Tijolo | D9: 0.4
A10: =B10&"-"&C10 -> Moderado-Híbridos | B10: Moderado | C10: Híbridos | D10: 0.08
A11: =B11&"-"&C11 -> Moderado-Desevolvimento | B11: Moderado | C11: Desevolvimento | D11: 0.05
A12: =B12&"-"&C12 -> Moderado-Hotelaria | B12: Moderado | C12: Hotelaria | D12: 0.05
A13: =B13&"-"&C13 -> Moderado-FOFs | B13: Moderado | C13: FOFs | D13: 0.1
... A19: =B19&"-"&C19 -> Agressivo-Hotelaria | B19: Agressivo | C19: Hotelaria | D19: 0.1
